nestargs/__init__.py
nestargs/_version.py
nestargs/parser.py
nestargs-1.1.0.dist-info/METADATA
nestargs-1.1.0.dist-info/WHEEL
nestargs-1.1.0.dist-info/licenses/LICENSE
nestargs-1.1.0.dist-info/RECORD
