Metadata-Version: 2.1
Name: nestargs
Version: 1.1.0
Summary: Nested arguments parser
Project-URL: Repository, https://github.com/speg03/nestargs
Author-email: Takahiro Yano <speg03@gmail.com>
License-Expression: MIT
License-File: LICENSE
Keywords: argparse,arguments,cli,command,interface,line,parser
Classifier: Development Status :: 4 - Beta
Classifier: Environment :: Console
Classifier: Intended Audience :: Developers
Classifier: License :: OSI Approved :: MIT License
Classifier: Operating System :: OS Independent
Classifier: Programming Language :: Python :: 3.8
Classifier: Programming Language :: Python :: 3.9
Classifier: Programming Language :: Python :: 3.10
Classifier: Programming Language :: Python :: 3.11
Classifier: Programming Language :: Python :: 3.12
Classifier: Topic :: Software Development :: Libraries :: Python Modules
Requires-Python: >=3.8
Provides-Extra: test
Requires-Dist: pytest; extra == 'test'
Requires-Dist: pytest-cov; extra == 'test'
